{
    "flux-framework/flux-core": [
        {
            "total": 22,
            "week": "2022-04-18"
        },
        {
            "total": 15,
            "week": "2022-04-25"
        },
        {
            "total": 6,
            "week": "2022-05-02"
        },
        {
            "total": 15,
            "week": "2022-05-09"
        },
        {
            "total": 11,
            "week": "2022-05-16"
        },
        {
            "total": 15,
            "week": "2022-05-23"
        },
        {
            "total": 26,
            "week": "2022-05-30"
        },
        {
            "total": 11,
            "week": "2022-06-06"
        },
        {
            "total": 14,
            "week": "2022-06-13"
        },
        {
            "total": 18,
            "week": "2022-06-20"
        },
        {
            "total": 27,
            "week": "2022-06-27"
        },
        {
            "total": 35,
            "week": "2022-07-04"
        },
        {
            "total": 16,
            "week": "2022-07-11"
        },
        {
            "total": 43,
            "week": "2022-07-18"
        },
        {
            "total": 29,
            "week": "2022-07-25"
        },
        {
            "total": 25,
            "week": "2022-08-01"
        },
        {
            "total": 23,
            "week": "2022-08-08"
        },
        {
            "total": 39,
            "week": "2022-08-15"
        },
        {
            "total": 40,
            "week": "2022-08-22"
        },
        {
            "total": 36,
            "week": "2022-08-29"
        },
        {
            "total": 36,
            "week": "2022-09-05"
        },
        {
            "total": 52,
            "week": "2022-09-12"
        },
        {
            "total": 63,
            "week": "2022-09-19"
        },
        {
            "total": 52,
            "week": "2022-09-26"
        },
        {
            "total": 54,
            "week": "2022-10-03"
        },
        {
            "total": 33,
            "week": "2022-10-10"
        },
        {
            "total": 43,
            "week": "2022-10-17"
        },
        {
            "total": 39,
            "week": "2022-10-24"
        },
        {
            "total": 16,
            "week": "2022-10-31"
        },
        {
            "total": 42,
            "week": "2022-11-07"
        },
        {
            "total": 16,
            "week": "2022-11-14"
        },
        {
            "total": 44,
            "week": "2022-11-21"
        },
        {
            "total": 43,
            "week": "2022-11-28"
        },
        {
            "total": 40,
            "week": "2022-12-05"
        },
        {
            "total": 7,
            "week": "2022-12-12"
        },
        {
            "total": 12,
            "week": "2022-12-19"
        },
        {
            "total": 5,
            "week": "2022-12-26"
        },
        {
            "total": 16,
            "week": "2023-01-02"
        },
        {
            "total": 19,
            "week": "2023-01-09"
        },
        {
            "total": 41,
            "week": "2023-01-16"
        },
        {
            "total": 29,
            "week": "2023-01-23"
        },
        {
            "total": 36,
            "week": "2023-01-30"
        },
        {
            "total": 48,
            "week": "2023-02-06"
        },
        {
            "total": 58,
            "week": "2023-02-13"
        },
        {
            "total": 61,
            "week": "2023-02-20"
        },
        {
            "total": 28,
            "week": "2023-02-27"
        },
        {
            "total": 17,
            "week": "2023-03-06"
        },
        {
            "total": 27,
            "week": "2023-03-13"
        },
        {
            "total": 73,
            "week": "2023-03-20"
        },
        {
            "total": 19,
            "week": "2023-03-27"
        },
        {
            "total": 49,
            "week": "2023-04-03"
        },
        {
            "total": 0,
            "week": "2023-04-10"
        }
    ]
}